gquote/__init__.py
gquote/__main__.py
gquote/fonts/Barkentina.ttf
gquote/fonts/Ubuntu-Italic.ttf
gquote-3.0.0.dist-info/LICENSE
gquote-3.0.0.dist-info/METADATA
gquote-3.0.0.dist-info/WHEEL
gquote-3.0.0.dist-info/top_level.txt
gquote-3.0.0.dist-info/zip-safe
gquote-3.0.0.dist-info/RECORD
